quackling/__init__.py
quackling/core/__init__.py
quackling/core/chunkers/__init__.py
quackling/core/chunkers/base.py
quackling/core/chunkers/hierarchical_chunker.py
quackling/langchain/__init__.py
quackling/langchain/loaders/__init__.py
quackling/langchain/loaders/base.py
quackling/langchain/loaders/docling_pdf_loader.py
quackling/langchain/splitters/__init__.py
quackling/langchain/splitters/hier_json_splitter.py
quackling/llama_index/__init__.py
quackling/llama_index/node_parsers/__init__.py
quackling/llama_index/node_parsers/base.py
quackling/llama_index/node_parsers/hier_node_parser.py
quackling/llama_index/readers/__init__.py
quackling/llama_index/readers/base.py
quackling/llama_index/readers/docling_json_reader.py
quackling/llama_index/readers/docling_pdf_reader.py
quackling/llama_index/readers/docling_reader.py
quackling/py.typed
quackling-0.4.1.dist-info/LICENSE
quackling-0.4.1.dist-info/METADATA
quackling-0.4.1.dist-info/WHEEL
quackling-0.4.1.dist-info/RECORD
