Metadata-Version: 2.1
Name: quackling
Version: 0.4.1
Summary: Quackling enables document-native generative AI applications
Home-page: https://github.com/DS4SD/quackling
License: MIT
Keywords: document,PDF,RAG,generative AI,chunking,docling,llama index
Author: Panos Vagenas
Author-email: pva@zurich.ibm.com
Maintainer: Panos Vagenas
Maintainer-email: pva@zurich.ibm.com
Requires-Python: >=3.10,<4.0
Classifier: Development Status :: 5 - Production/Stable
Classifier: Intended Audience :: Developers
Classifier: Intended Audience :: Science/Research
Classifier: License :: OSI Approved :: MIT License
Classifier: Natural Language :: English
Classifier: Operating System :: OS Independent
Classifier: Programming Language :: Python :: 3
Classifier: Programming Language :: Python :: 3.10
Classifier: Programming Language :: Python :: 3.11
Classifier: Programming Language :: Python :: 3.12
Classifier: Topic :: Scientific/Engineering :: Artificial Intelligence
Classifier: Topic :: Software Development :: Libraries :: Python Modules
Classifier: Typing :: Typed
Provides-Extra: examples
Requires-Dist: docling (>=1.8.2,<2.0.0)
Requires-Dist: docling-core (>=1.1.2,<2.0.0)
Requires-Dist: flagembedding (>=1.2.10,<2.0.0) ; extra == "examples"
Requires-Dist: jsonpath-ng (>=1.6.1,<2.0.0) ; extra == "examples"
Requires-Dist: langchain-core (>=0.2.38,<0.3.0)
Requires-Dist: langchain-huggingface (>=0.0.3,<0.0.4) ; extra == "examples"
Requires-Dist: langchain-milvus (>=0.1.4,<0.2.0) ; extra == "examples"
Requires-Dist: langchain-text-splitters (>=0.2.4,<0.3.0) ; extra == "examples"
Requires-Dist: llama-index-core (>=0.11.1,<0.12.0)
Requires-Dist: llama-index-embeddings-huggingface (>=0.3.1,<0.4.0) ; extra == "examples"
Requires-Dist: llama-index-llms-huggingface-api (>=0.2.0,<0.3.0) ; extra == "examples"
Requires-Dist: llama-index-postprocessor-flag-embedding-reranker (>=0.2.0,<0.3.0) ; extra == "examples"
Requires-Dist: llama-index-vector-stores-milvus (>=0.2.1,<0.3.0) ; extra == "examples"
Requires-Dist: peft (>=0.12.0,<0.13.0) ; extra == "examples"
Requires-Dist: python-dotenv (>=1.0.1,<2.0.0) ; extra == "examples"
Requires-Dist: torch (>=2.2.2,<2.3.0) ; sys_platform == "darwin" and platform_machine == "x86_64"
Requires-Dist: torch (>=2.2.2,<3.0.0) ; sys_platform != "darwin" or platform_machine != "x86_64"
Requires-Dist: torchvision (>=0,<1) ; sys_platform != "darwin" or platform_machine != "x86_64"
Requires-Dist: torchvision (>=0.17.2,<0.18.0) ; sys_platform == "darwin" and platform_machine == "x86_64"
Project-URL: Repository, https://github.com/DS4SD/quackling
